word2Tex/__init__.py
word2Tex/cite2Tex.py
word2Tex/doi2bib.py
word2Tex/fixBibTex.py
word2Tex-0.0.17.dist-info/LICENSE
word2Tex-0.0.17.dist-info/METADATA
word2Tex-0.0.17.dist-info/WHEEL
word2Tex-0.0.17.dist-info/entry_points.txt
word2Tex-0.0.17.dist-info/top_level.txt
word2Tex-0.0.17.dist-info/RECORD
