Metadata-Version: 2.1
Name: word2Tex
Version: 0.0.17
Summary: package for moving manuscripts from Word to LaTeX
Home-page: https://github.com/nubs01/word2Tex
Author: Roshan Nanu
Author-email: roshan.nanu@gmail.com
License: MIT
Keywords: word2Tex cite2Tex fixBibTex bibtex latex Word citation cite convert
Platform: UNKNOWN
Classifier: Programming Language :: Python :: 3.6
Classifier: Programming Language :: Python :: 3.7
Classifier: Operating System :: OS Independent
Classifier: License :: OSI Approved :: MIT License
Requires-Python: >=3.6
Requires-Dist: pandas
Requires-Dist: bibtexparser (>=1.2)
Requires-Dist: requests
